odoo/addons/l10n_th_base_utils/README.rst
odoo/addons/l10n_th_base_utils/__init__.py
odoo/addons/l10n_th_base_utils/__manifest__.py
odoo/addons/l10n_th_base_utils/i18n/l10n_th_base_utils.pot
odoo/addons/l10n_th_base_utils/models/__init__.py
odoo/addons/l10n_th_base_utils/models/res_company.py
odoo/addons/l10n_th_base_utils/models/thai_utils.py
odoo/addons/l10n_th_base_utils/readme/CONFIGURE.md
odoo/addons/l10n_th_base_utils/readme/CONTRIBUTORS.md
odoo/addons/l10n_th_base_utils/readme/DESCRIPTION.md
odoo/addons/l10n_th_base_utils/readme/USAGE.md
odoo/addons/l10n_th_base_utils/static/description/icon.png
odoo/addons/l10n_th_base_utils/static/description/index.html
odoo/addons/l10n_th_base_utils/static/fonts/AngsanaNew.ttf
odoo/addons/l10n_th_base_utils/static/fonts/THBaijam.ttf
odoo/addons/l10n_th_base_utils/static/fonts/THChakraPetch.ttf
odoo/addons/l10n_th_base_utils/static/fonts/THCharmofAU.ttf
odoo/addons/l10n_th_base_utils/static/fonts/THCharmonman.ttf
odoo/addons/l10n_th_base_utils/static/fonts/THFahkwang.ttf
odoo/addons/l10n_th_base_utils/static/fonts/THK2DJuly8.ttf
odoo/addons/l10n_th_base_utils/static/fonts/THKoHo.ttf
odoo/addons/l10n_th_base_utils/static/fonts/THKodchasal.ttf
odoo/addons/l10n_th_base_utils/static/fonts/THKrub.ttf
odoo/addons/l10n_th_base_utils/static/fonts/THMaliGrade6.ttf
odoo/addons/l10n_th_base_utils/static/fonts/THNiramitAS.ttf
odoo/addons/l10n_th_base_utils/static/fonts/THSarabun.ttf
odoo/addons/l10n_th_base_utils/static/fonts/THSarabunNew.ttf
odoo/addons/l10n_th_base_utils/static/fonts/THSrisakdi.ttf
odoo/addons/l10n_th_base_utils/static/fonts/Webdings.ttf
odoo/addons/l10n_th_base_utils/static/src/scss/fonts_style.scss
odoo/addons/l10n_th_base_utils/tests/__init__.py
odoo/addons/l10n_th_base_utils/tests/test_l10n_th_base_utils.py
odoo_addon_l10n_th_base_utils-18.0.2.0.0.dist-info/METADATA
odoo_addon_l10n_th_base_utils-18.0.2.0.0.dist-info/WHEEL
odoo_addon_l10n_th_base_utils-18.0.2.0.0.dist-info/top_level.txt
odoo_addon_l10n_th_base_utils-18.0.2.0.0.dist-info/RECORD
