Metadata-Version: 2.1
Name: odoo-addon-l10n_th_base_utils
Version: 18.0.2.0.0
Requires-Python: >=3.10
Requires-Dist: odoo==18.0.*
Summary: Collection of all Thai fonts, Convert month/year/number to thai
Home-page: https://github.com/OCA/l10n-thailand
License: AGPL-3
Author: Ecosoft, Odoo Community Association (OCA)
Author-email: support@odoo-community.org
Classifier: Programming Language :: Python
Classifier: Framework :: Odoo
Classifier: Framework :: Odoo :: 18.0
Classifier: License :: OSI Approved :: GNU Affero General Public License v3
